{
  "$schema": "https://schemas.wp.org/trunk/block.json",
  "apiVersion": 2,
  "name": "material/hamburger-menu",
  "textdomain": "material-design-google",
  "category": "material",
  "title": "Material Header Hamburger Menu",
  "supports": {},
  "description": "Material hamburger icon which expands to show menu drawer on click.",
  "editorStyle": "material-block-editor-css-theme",
  "editorScript": "material-block-editor-js-theme",
  "attributes": {
    "isDrawerOpen": {
      "type": "boolean",
      "default": false
    }
  },
  "providesContext": {
    "material/isDrawerOpen": "isDrawerOpen"
  }
}
